diamond_art/__init__.py
diamond_art/cli.py
diamond_art/diamond_art.py
diamond_art/data/__init__.py
diamond_art/data/fonts/__init__.py
diamond_art/data/fonts/Noto_Sans_Symbols/NotoSansSymbols-Regular.ttf
diamond_art/data/fonts/Noto_Sans_Symbols/OFL.txt
diamond_art/data/fonts/Noto_Sans_Symbols/README.txt
diamond_art/data/fonts/Noto_Sans_Symbols/__init__.py
diamond_art-0.1.0.dist-info/AUTHORS.md
diamond_art-0.1.0.dist-info/LICENSE
diamond_art-0.1.0.dist-info/METADATA
diamond_art-0.1.0.dist-info/WHEEL
diamond_art-0.1.0.dist-info/entry_points.txt
diamond_art-0.1.0.dist-info/top_level.txt
diamond_art-0.1.0.dist-info/zip-safe
diamond_art-0.1.0.dist-info/RECORD
