Metadata-Version: 2.1
Name: diamond-art
Version: 0.1.0
Summary: Convert pixel images to diamond art templates
Home-page: https://github.com/sbliven/diamond_art
Author: Spencer Bliven
Author-email: spencer.bliven@gmail.com
License: BSD license
Keywords: diamond_art
Platform: UNKNOWN
Classifier: Development Status :: 2 - Pre-Alpha
Classifier: Intended Audience :: Developers
Classifier: License :: OSI Approved :: BSD License
Classifier: Natural Language :: English
Classifier: Programming Language :: Python :: 3
Classifier: Programming Language :: Python :: 3.7
Classifier: Programming Language :: Python :: 3.8
Classifier: Programming Language :: Python :: 3.9
Requires-Python: >=3.5
License-File: LICENSE
License-File: AUTHORS.md
Requires-Dist: Click (>=7.0)
Requires-Dist: pillow
Requires-Dist: numpy
Provides-Extra: dev
Requires-Dist: bump2version ; extra == 'dev'
Requires-Dist: twine ; extra == 'dev'
Requires-Dist: tox ; extra == 'dev'
Requires-Dist: flake8 ; extra == 'dev'
Requires-Dist: black ; extra == 'dev'
Requires-Dist: mypy ; extra == 'dev'
Requires-Dist: isort ; extra == 'dev'
Requires-Dist: pytest ; extra == 'dev'
Provides-Extra: tests
Requires-Dist: tox ; extra == 'tests'
Requires-Dist: flake8 ; extra == 'tests'
Requires-Dist: black ; extra == 'tests'
Requires-Dist: mypy ; extra == 'tests'
Requires-Dist: isort ; extra == 'tests'
Requires-Dist: pytest ; extra == 'tests'
